bluecatnovamonitor/__init__.py
bluecatnovamonitor-0.0.2.dist-info/DESCRIPTION.rst
bluecatnovamonitor-0.0.2.dist-info/METADATA
bluecatnovamonitor-0.0.2.dist-info/RECORD
bluecatnovamonitor-0.0.2.dist-info/WHEEL
bluecatnovamonitor-0.0.2.dist-info/metadata.json
bluecatnovamonitor-0.0.2.dist-info/top_level.txt
