Metadata-Version: 2.0
Name: bluecatnovamonitor
Version: 0.0.2
Summary: BlueCat Nova Monitor
Home-page: https://github.com/bshorland/bluecatnovamonitor
Author: Brian Shorland
Author-email: bshorland@bluecatnetworks.com
License: BSD
Download-URL: https://github.com/bshorland/bluecatnovamonitor/tarball/0.0.2
Platform: UNKNOWN
Classifier: Development Status :: 3 - Alpha
Classifier: Intended Audience :: Developers
Classifier: Programming Language :: Python :: 3
Requires-Dist: dnspython
